recentrifuge/__init__.py
recentrifuge/centrifuge.py
recentrifuge/centrifuge_io.py
recentrifuge/clark.py
recentrifuge/config.py
recentrifuge/core.py
recentrifuge/fastq_io.py
recentrifuge/gene_ontology.py
recentrifuge/generic.py
recentrifuge/go.py
recentrifuge/kraken.py
recentrifuge/krona.js
recentrifuge/krona.py
recentrifuge/lmat.py
recentrifuge/lmat_io.py
recentrifuge/mock.py
recentrifuge/ontology.py
recentrifuge/params.py
recentrifuge/rank.py
recentrifuge/shared_counter.py
recentrifuge/stats.py
recentrifuge/taxclass.py
recentrifuge/taxonomy.py
recentrifuge/trees.py
recentrifuge/img/favicon.uri
recentrifuge/img/hidden.uri
recentrifuge/img/loading.uri
recentrifuge/img/logo-rcf-mini.uri
recentrifuge/img/logo-rgf-mini.uri
recentrifuge/test/TEST.rcf.html
recentrifuge/test/TEST.rcf.xlsx
recentrifuge/test/ctrl1.mck
recentrifuge/test/ctrl2.mck
recentrifuge/test/ctrl3.mck
recentrifuge/test/mock.xlsx
recentrifuge/test/smpl1.mck
recentrifuge/test/smpl2.mck
recentrifuge/test/smpl3.mck
recentrifuge-2.0.0.data/scripts/rcf
recentrifuge-2.0.0.data/scripts/refafilt
recentrifuge-2.0.0.data/scripts/refasplit
recentrifuge-2.0.0.data/scripts/remock
recentrifuge-2.0.0.data/scripts/retaxdump
recentrifuge-2.0.0.data/scripts/retest
recentrifuge-2.0.0.data/scripts/rextraccnt
recentrifuge-2.0.0.data/scripts/rextract
recentrifuge-2.0.0.data/scripts/rgf
recentrifuge-2.0.0.dist-info/licenses/COPYING.txt
recentrifuge-2.0.0.dist-info/licenses/LICENSE.txt
recentrifuge-2.0.0.dist-info/METADATA
recentrifuge-2.0.0.dist-info/WHEEL
recentrifuge-2.0.0.dist-info/top_level.txt
recentrifuge-2.0.0.dist-info/RECORD
