Metadata-Version: 2.4
Name: recentrifuge
Version: 2.0.0
Summary: Robust comparative analysis and contamination removal for metagenomics
Author-email: Jose Manuel Martí <jse.mnl@gmail.com>
License-Expression: AGPL-3.0-or-later
Project-URL: Homepage, http://www.recentrifuge.org
Project-URL: Documentation, https://github.com/khyox/recentrifuge/wiki
Project-URL: Repository, https://github.com/khyox/recentrifuge
Project-URL: Issues, https://github.com/khyox/recentrifuge/issues
Keywords: metagenomics,comparative-analysis,contamination-removal
Classifier: Development Status :: 5 - Production/Stable
Classifier: Environment :: Console
Classifier: Environment :: Web Environment
Classifier: Intended Audience :: Science/Research
Classifier: Natural Language :: English
Classifier: Operating System :: OS Independent
Classifier: Programming Language :: JavaScript
Classifier: Programming Language :: Python :: 3.12
Classifier: Programming Language :: Python :: 3.13
Classifier: Programming Language :: Python :: 3.14
Classifier: Topic :: Scientific/Engineering :: Bio-Informatics
Classifier: Topic :: Scientific/Engineering :: Medical Science Apps.
Requires-Python: >=3.12
License-File: LICENSE.txt
License-File: COPYING.txt
Requires-Dist: biopython==1.84
Requires-Dist: numpy>=2.3.4
Requires-Dist: openpyxl>=3.1.2
Requires-Dist: matplotlib>=3.3.4
Requires-Dist: pandas>=2.3.3
Dynamic: license-file
